eogrow/__init__.py
eogrow/cli.py
eogrow/eo-grow.code-workspace
eogrow/py.typed
eogrow/types.py
eogrow/core/__init__.py
eogrow/core/base.py
eogrow/core/config.py
eogrow/core/logging.py
eogrow/core/pipeline.py
eogrow/core/schemas.py
eogrow/core/storage.py
eogrow/core/area/__init__.py
eogrow/core/area/base.py
eogrow/core/area/custom_grid.py
eogrow/core/area/utm.py
eogrow/pipelines/__init__.py
eogrow/pipelines/batch_to_eopatch.py
eogrow/pipelines/byoc.py
eogrow/pipelines/download.py
eogrow/pipelines/download_batch.py
eogrow/pipelines/export_maps.py
eogrow/pipelines/features.py
eogrow/pipelines/import_tiff.py
eogrow/pipelines/import_vector.py
eogrow/pipelines/merge_samples.py
eogrow/pipelines/prediction.py
eogrow/pipelines/rasterize.py
eogrow/pipelines/sampling.py
eogrow/pipelines/split_grid.py
eogrow/pipelines/testing.py
eogrow/pipelines/training.py
eogrow/pipelines/zipmap.py
eogrow/tasks/__init__.py
eogrow/tasks/batch_to_eopatch.py
eogrow/tasks/common.py
eogrow/tasks/features.py
eogrow/tasks/prediction.py
eogrow/tasks/spatial.py
eogrow/tasks/testing.py
eogrow/utils/__init__.py
eogrow/utils/batch.py
eogrow/utils/eopatch_list.py
eogrow/utils/filter.py
eogrow/utils/fs.py
eogrow/utils/general.py
eogrow/utils/grid.py
eogrow/utils/logging.py
eogrow/utils/map.py
eogrow/utils/meta.py
eogrow/utils/pipeline_chain.py
eogrow/utils/ray.py
eogrow/utils/testing.py
eogrow/utils/validators.py
eogrow/utils/vector.py
eogrow/utils/zipmap.py
eo_grow-1.7.15.dist-info/METADATA
eo_grow-1.7.15.dist-info/WHEEL
eo_grow-1.7.15.dist-info/entry_points.txt
eo_grow-1.7.15.dist-info/licenses/LICENSE
eo_grow-1.7.15.dist-info/RECORD
