Metadata-Version: 2.4
Name: eo-grow
Version: 1.7.15
Summary: Earth observation framework for scaled-up processing in Python
Project-URL: Homepage, https://github.com/sentinel-hub/eo-grow
Project-URL: Documentation, https://eo-grow.readthedocs.io
Project-URL: Issues, https://github.com/sentinel-hub/eo-grow/issues
Project-URL: Source, https://github.com/sentinel-hub/eo-grow
Project-URL: Forum, https://forum.sentinel-hub.com
Author-email: Sinergise EO research team <eoresearch@sinergise.com>
License: MIT License
License-File: LICENSE
Classifier: Development Status :: 5 - Production/Stable
Classifier: Intended Audience :: Developers
Classifier: Intended Audience :: Education
Classifier: Intended Audience :: Science/Research
Classifier: License :: OSI Approved :: MIT License
Classifier: Operating System :: MacOS
Classifier: Operating System :: Microsoft :: Windows
Classifier: Operating System :: Unix
Classifier: Programming Language :: Python
Classifier: Programming Language :: Python :: 3
Classifier: Programming Language :: Python :: 3.8
Classifier: Programming Language :: Python :: 3.9
Classifier: Programming Language :: Python :: 3.10
Classifier: Programming Language :: Python :: 3.11
Classifier: Topic :: Scientific/Engineering
Classifier: Topic :: Scientific/Engineering :: GIS
Classifier: Topic :: Scientific/Engineering :: Image Processing
Requires-Python: >=3.9
Requires-Dist: boto3<=1.29.6
Requires-Dist: click
Requires-Dist: colorlog
Requires-Dist: eo-learn[visualization]>=1.5.0
Requires-Dist: fiona>=1.8.18
Requires-Dist: fs>=2.2.0
Requires-Dist: geopandas<1,>=0.14.4
Requires-Dist: numpy
Requires-Dist: opencv-python-headless
Requires-Dist: pandas
Requires-Dist: pydantic<2.0,>=1.8.0
Requires-Dist: python-dateutil
Requires-Dist: python-rapidjson
Requires-Dist: rasterio
Requires-Dist: ray[default]
Requires-Dist: sentinelhub>=3.9.0
Requires-Dist: shapely>=1.8.0
Requires-Dist: typing-extensions>=4.5.0
Provides-Extra: dev
Requires-Dist: boto3; extra == 'dev'
Requires-Dist: boto3-stubs; extra == 'dev'
Requires-Dist: build; extra == 'dev'
Requires-Dist: deepdiff; extra == 'dev'
Requires-Dist: fs-s3fs; extra == 'dev'
Requires-Dist: joblib; extra == 'dev'
Requires-Dist: lightgbm>=3.0.0; extra == 'dev'
Requires-Dist: moto[s3]>=5.0.0; extra == 'dev'
Requires-Dist: mypy>=0.990; extra == 'dev'
Requires-Dist: numpy>=2.0.0; extra == 'dev'
Requires-Dist: pre-commit; extra == 'dev'
Requires-Dist: pyogrio; extra == 'dev'
Requires-Dist: pytest-cov; extra == 'dev'
Requires-Dist: pytest-order; extra == 'dev'
Requires-Dist: pytest>=4.0.0; extra == 'dev'
Requires-Dist: requests-mock; extra == 'dev'
Requires-Dist: scikit-learn; extra == 'dev'
Requires-Dist: scipy; extra == 'dev'
Requires-Dist: twine; extra == 'dev'
Requires-Dist: types-mock; extra == 'dev'
Requires-Dist: types-python-dateutil; extra == 'dev'
Requires-Dist: types-requests; extra == 'dev'
Requires-Dist: types-setuptools; extra == 'dev'
Requires-Dist: types-urllib3; extra == 'dev'
Provides-Extra: docs
Requires-Dist: autodoc-pydantic; extra == 'docs'
Requires-Dist: nbsphinx; extra == 'docs'
Requires-Dist: sphinx-mdinclude==0.5.4; extra == 'docs'
Requires-Dist: sphinx-rtd-theme==1.3.0; extra == 'docs'
Requires-Dist: sphinx==7.1.2; extra == 'docs'
Provides-Extra: ml
Requires-Dist: joblib; extra == 'ml'
Requires-Dist: lightgbm>=3.0.0; extra == 'ml'
Requires-Dist: scikit-learn; extra == 'ml'
